LICENSE
README.md
setup.py
arctic_connection/__init__.py
arctic_connection/arctic_connection.py
arctic_connection.egg-info/PKG-INFO
arctic_connection.egg-info/SOURCES.txt
arctic_connection.egg-info/dependency_links.txt
arctic_connection.egg-info/requires.txt
arctic_connection.egg-info/top_level.txt